pileups/__init__.py
pileups/allelecounts.py
pileups/pileups.py
pileups/pileups_count.py
pileups/pileups_dist.py
pileups/pileups_intersect.py
pileups/pileups_merge.py
pileups/pileups_merge_counts.py
pileups-0.3.6.dist-info/LICENSE
pileups-0.3.6.dist-info/METADATA
pileups-0.3.6.dist-info/WHEEL
pileups-0.3.6.dist-info/entry_points.txt
pileups-0.3.6.dist-info/top_level.txt
pileups-0.3.6.dist-info/RECORD
