Metadata-Version: 2.1
Name: pileups
Version: 0.3.6
Summary: Manipulate files of the pileup format from SAMtools
Home-page: https://gitlab.com/aaylward/pileups
Author: Anthony Aylward
Author-email: aaylward@salk.edu
License: UNKNOWN
Platform: UNKNOWN
Classifier: Programming Language :: Python :: 3
Classifier: License :: OSI Approved :: MIT License
Classifier: Operating System :: OS Independent
License-File: LICENSE
Requires-Dist: funcgenom
